spotibox/__init__.py
spotibox/albums.py
spotibox/cli.py
spotibox/spotibox.py
spotibox-0.2.0.dist-info/AUTHORS.rst
spotibox-0.2.0.dist-info/LICENSE
spotibox-0.2.0.dist-info/METADATA
spotibox-0.2.0.dist-info/WHEEL
spotibox-0.2.0.dist-info/entry_points.txt
spotibox-0.2.0.dist-info/top_level.txt
spotibox-0.2.0.dist-info/RECORD
