Metadata-Version: 2.1
Name: spotibox
Version: 0.2.0
Summary: Spotify player for kids running on RaspberryPi with GPIO controls
Home-page: https://github.com/martinhanewald/spotibox
Author: Martin Hanewald
Author-email: martin.hanewald@gmail.com
License: MIT license
Keywords: spotibox
Platform: UNKNOWN
Classifier: Development Status :: 2 - Pre-Alpha
Classifier: Intended Audience :: Developers
Classifier: License :: OSI Approved :: MIT License
Classifier: Natural Language :: English
Classifier: Programming Language :: Python :: 3
Classifier: Programming Language :: Python :: 3.6
Classifier: Programming Language :: Python :: 3.7
Classifier: Programming Language :: Python :: 3.8
Requires-Python: >=3.6
Requires-Dist: Click (>=7.0)
Requires-Dist: gpiozero
Requires-Dist: spotipy
